{
    "version": "https://jsonfeed.org/version/1",
    "title": "It's a blog • All posts by \"英文\" category",
    "description": "",
    "home_page_url": "https://utgnim.github.io",
    "items": [
        {
            "id": "https://utgnim.github.io/short-English-sentence/",
            "url": "https://utgnim.github.io/short-English-sentence/",
            "title": "short English sentence",
            "date_published": "2026-04-12T09:52:41.000Z",
            "content_html": "<p>As for worrying about what other people might think, forget it. They aren’t concerned about you. They’re too busy worrying about what you and other people think of them.</p>\n<p>The greatest of follies is to sacrifice health for any other kind of happiness.</p>\n<p>Sometimes life is going to hit you in the head with a brick. Don’t lose faith.</p>\n<p>There are two means of refuge from the miseries of life: music and cats.</p>\n<p>“Careful with fire” is good advice we know. “Careful with words” is ten times doubly so.</p>\n<p>Fight for your opinions, but do not believe that they contain the whole truth, or the only truth.</p>\n<p>Life gives you a comb after you lose your hair.</p>\n<p>I’m going to memorize your name and throw my head away.</p>\n<p>There is a sacredness in tears. They are not the mark of weakness, but of power.</p>\n<p>Hypocrisy can afford to be magnificent in its promises, for never intending to go beyond promise, it costs nothing.</p>\n<p>Your pain is the breaking of the shell that encloses your understanding.</p>\n<p>Logic merely enables one to be wrong with authority.</p>\n<p>Constantly talking isn’t necessarily communicating.</p>\n<p>Nothing can cure the soul but the senses, just as nothing can cure the senses but the soul.</p>\n<p>Another belief of mine: that everyone else my age is an adult, whereas I am merely in disguise.</p>\n<p>To obtain a man’s opinion of you, make him mad.</p>\n<p>In great attempts, it is even glorious to fail.</p>\n<p>It is easier to resist at the beginning than at the end.</p>\n<p>The fact that an opinion has been widely held is no evidence whatever that it is not utterly absurd.</p>\n<p>Begin at the beginning, and go on until you come to the end; then stop.</p>\n<p>The beauty of a woman is not in the clothes she wears, the figure that she carries or the way she combs her hair.</p>\n<p>What we obtain too cheaply, we esteem too lightly; it’s dearness only that gives everything its value.</p>\n<p>Home is not where you live but where they understand you.</p>\n<p>It is certainly desirable to be well descended, but the glory belongs to our ancestors.</p>\n<p>Anyone can do any amount of work provided it isn’t the work he is supposed to be doing at the moment.</p>\n<p>You cannot shake hands with a clenched fist.</p>\n<p>Sometimes I have thought it would be an excellent rule to live each day as if we should die tomorrow.</p>\n<p>Don’t try to win a friend by presenting gifts.</p>\n<p>The more you experience and appreciate the goodness of life, the more there is to be lived.</p>\n<p>What greater blessing than to be with those you love, and to feel that every heart beats in harmony.</p>\n<p>Love is a choice. It is a conscious commitment. It is something you choose to make work every day with a person who has chosen the same thing.</p>\n<p>Not I - not anyone else, can travel that road for you, You must travel it for yourself.</p>\n<p>The golden rule is that there are no golden rules.</p>\n<p>Our anxiety does not come from thinking about the future, but from wanting to control it.</p>\n<p>Things change. And friends leave. Life doesn’t stop for anybody.</p>\n<p>The way you treat yourself sets the standard for others.  </p>\n<p>To avoid criticism, do nothing, say nothing and be nothing.</p>\n<p>The most wasted of days is one without laughter.</p>\n<p>The power of imagination created the illusion that my vision went much farther than the naked eye could actually see.</p>\n<p>Nothing is so strong as gentleness, nothing so gentle as real strength.</p>\n<p>No winter lasts forever; no spring skips its turn.</p>\n<p>What is essential is invisible to the eye.</p>\n<p>The quieter you become, the more you can hear.</p>\n<p>There is no greater agony than bearing an untold story inside you.</p>\n<p>You and I who still enjoy fairy tales have less reason to wish actual childhood back. We have kept its pleasures and added some grown-up ones as well. </p>\n<p>There are two ways of getting home; and one of them is to stay there. </p>\n<p>There are far, far better things ahead than any we leave behind.</p>\n<p>Waiting is painful. Forgetting is painful. But not knowing which to do is the worst kind of suffering.</p>\n<p>There is only one success - to be able to spend your life in your own way. </p>\n<p>Either write things worth reading, or do things worth writing.</p>\n<p>It’s no use going back to yesterday, because I was a different person then. </p>\n<p>The true triumph of reason is that it enables us to get along with those who do not possess it.</p>\n<p>Health is the pillar of the soul and an important foundation.</p>\n<p>Destiny is like a dust storm; you have nowhere to hide.</p>\n<p>Curious things, habits. People themselves never knew they had them. </p>\n<p>If you can feel pain, you are alive; if you can feel the pain of others, you are human.</p>\n<p>There are three classes of people: those who see, those who see when they are shown, those who do not see.</p>\n<p>To be without some of the things you want is an indispensable part of happiness.</p>\n<p>The dignity and glory of the person lies not in sophistication but in honesty.</p>\n<p>It is difficult to find happiness within oneself, but it is impossible to find it anywhere else.</p>\n<p>You will never have what you like until you learn to like what you have.</p>\n<p>It is in our faults and mistakes, not in our virtues, that we touch each other and find resonance. Our essence lies in our absurdities.</p>\n<p>The only true wisdom is in knowing you know nothing.</p>\n<p>What lies behind us and what lies before us are tiny matters compared to what lies within us.</p>\n<p>Life isn’t about waiting for the storm to pass. It’s about learning how to dance in the rain.</p>\n<p>We must accept finite disappointment, but we must never lose infinite hope.</p>\n<p>Every snowflake is a masterpiece of patience.</p>\n<p>Courage is grace under pressure.</p>\n<p>We don’t see things as they are, we see them as we are.</p>\n<p>The art of being wise is knowing what to overlook.</p>\n<p>The past is a place of reference, not a place of residence; the past is a place of learning, not a place of living.</p>\n<p>The greatest wealth is to live content with little.</p>\n<p>We either make ourselves miserable, or we make ourselves strong. The amount of work is the same.</p>\n<p>I would rather sit on a pumpkin, and have it all to myself, than be crowded on a velvet cushion.</p>\n<p>Do not wait for leaders; do it alone, person to person.</p>\n<p>No one can make you feel inferior without your consent.</p>\n<p>He who is of a calm and happy nature will hardly feel the pressure of age, but to him who is of an opposite disposition, youth and age are equally a burden.</p>\n<p>You run from one place to another, but you are still you. You can’t escape from your body.</p>\n<p>A lie can travel halfway around the world while the truth is still putting on its shoes.</p>\n<p>I have approximate answers and possible beliefs and different degrees of certainty about different things… It doesn’t frighten me.</p>\n<p>No man is really happy or safe without a hobby.</p>\n<p>Understanding is the first step to acceptance, and only with acceptance can there be recovery.</p>\n<p>We can never know things as they are in themselves, only as they appear to us. </p>\n<p>We are all like the bright moon; we still have our darker side.</p>\n<p>The content of your character is your choice. Day by day, what you choose, what you think and what you do is who you become.</p>\n<p>One should sympathize with the color, the beauty, the joy of life. The less said about life’s sores the better.</p>\n<p>Do not say a little in many words but a great deal in a few.</p>\n<p>I can resist everything except temptation.</p>\n<p>The soul becomes dyed with the color of its thoughts.</p>\n<p>We may give advice, but we can’t give conduct.</p>\n",
            "tags": [
                "抄书",
                "练字"
            ]
        },
        {
            "id": "https://utgnim.github.io/%E6%96%B0%E6%A6%82%E5%BF%B5%E8%8B%B1%E8%AF%AD-%E7%AC%AC-1-%E5%86%8C/",
            "url": "https://utgnim.github.io/%E6%96%B0%E6%A6%82%E5%BF%B5%E8%8B%B1%E8%AF%AD-%E7%AC%AC-1-%E5%86%8C/",
            "title": "新概念英语 - 第 1 册",
            "date_published": "2025-07-15T14:00:20.000Z",
            "content_html": "<h4 id=\"Excuse-me\"><a href=\"#Excuse-me\" class=\"headerlink\" title=\"Excuse me\"></a>Excuse me</h4><p>Excuse me!<br>Yes?<br>Is this your handbag?<br>Pardon?<br>Is this your handbag?<br>Yes, it is.<br>Thank you very much.</p>\n<h4 id=\"Sorry-sir\"><a href=\"#Sorry-sir\" class=\"headerlink\" title=\"Sorry sir\"></a>Sorry sir</h4><p>My coat and my umbrella please.<br>Here is my tickets.<br>Thank you, sir.<br>Number five.<br>Here’s your umbrella and your coat.<br>This is not my umbrella.<br>Sorry sir.<br>Is this your umbrella?<br>No, it isn’t.<br>Is this it?<br>Yes, it is.<br>Thank you very much.</p>\n<h4 id=\"Nice-to-meet-you\"><a href=\"#Nice-to-meet-you\" class=\"headerlink\" title=\"Nice to meet you\"></a>Nice to meet you</h4><p>Good morning.<br>Good morning, Mr. Blake.<br>This is Miss Sophie Dupont.<br>Sophie is a new student. She is French.<br>Sophie, this is Hans. He is German.<br>Nice to meet you.<br>And this is Naoko. She’s Japanese.<br>Nice to meet you.<br>And this is Chang-woo. He’s Korean.<br>Nice to meet you.<br>And this is Luming. He is Chinese.<br>Nice to meet you.<br>And this is Xiaohui. Shie’s Chinese, too.<br>Nice to meet you.</p>\n<h4 id=\"Are-you-a-teacher\"><a href=\"#Are-you-a-teacher\" class=\"headerlink\" title=\"Are you a teacher\"></a>Are you a teacher</h4><p>I am a new student. My name’s Robert.<br>Nice to meet you. My name’s Sophie.<br>Are you French?<br>Yes, I am.<br>Are you French too?<br>No, I am not.<br>What nationality are you?<br>I’m Italian.<br>Are you a teacher?<br>No, I’m not.<br>What’s your job?<br>I’m a keyboard operator.<br>What’s your job?<br>I’m an engineer.</p>\n<h4 id=\"How-are-you-today\"><a href=\"#How-are-you-today\" class=\"headerlink\" title=\"How are you today\"></a>How are you today</h4><p>Hello, Helen.<br>Hi, Steven.<br>How are you today?<br>I’m very well, thank you. And you?<br>How is Tony?<br>He’s fine, thanks. How’s Emma?<br>She’s very well, too, Helen.<br>Goodbye, Helen. Nice to see you.<br>Nice to see you, too, Steven.<br>Goodbye.</p>\n<h4 id=\"Is-this-your-shirt\"><a href=\"#Is-this-your-shirt\" class=\"headerlink\" title=\"Is this your shirt\"></a>Is this your shirt</h4><p>Whose shirt is that?<br>Is this your shirt, Dave?<br>No. Sir. It’s not my shirt.<br>This is my shirt. My shirt’s blue.<br>Is this shirt Tim’s?<br>Perhaps it is, sir. Tim’s shirt’s white.<br>Tim!<br>Yes, sir?<br>Is this your shirt?<br>Yes, sir.<br>Here you are. Catch!<br>Thank you. sir.</p>\n<h4 id=\"A-New-Dress\"><a href=\"#A-New-Dress\" class=\"headerlink\" title=\"A New Dress\"></a>A New Dress</h4><p>What color’s your new dress?<br>It’s green.<br>Come upstairs and see it.<br>Thank you.<br>Look! Here it is!<br>That’s a nice dress. It’s very smart.<br>My hat’s new, too.<br>What colour is it?<br>It’s the same colour. It’s green, too.<br>That is a lovely hat!</p>\n<h4 id=\"You-passports-please\"><a href=\"#You-passports-please\" class=\"headerlink\" title=\"You passports please\"></a>You passports please</h4><p>Are you Swedish?<br>No, we are not. We are Danish.<br>Are your friends Danish, too?<br>No, they aren’t. They are Norwegian.<br>Your passports, please.<br>Here they are.<br>Are these your cases?<br>No, they aren’t.<br>Our cases are brown. Here they are.<br>Are you tourists?<br>Yes, we are.<br>Are your friends tourists too?<br>Yes, they are.<br>That’s fine.<br>Thank you very much.</p>\n<h4 id=\"How-do-you-do\"><a href=\"#How-do-you-do\" class=\"headerlink\" title=\"How do you do\"></a>How do you do</h4><p>Come and meet our  employees, Mr. Richards.<br>Thank you, Mr, Jackson.<br>This is Nicola Grey, and this is Claire Taylor.<br>How do you do?<br>Those women are very hard-working.<br>What are their jobs?<br>They’re keyboard operators.<br>This is Michael Baker, and this is Jeremy Short.<br>How do you do?<br>They aren’t very busy!<br>What are their jobs?<br>They’re sales reps.<br>They are very lazy.<br>Who is this young man?<br>This is Jim.<br>He is our office assistant.</p>\n<h4 id=\"Tired-and-thirsty\"><a href=\"#Tired-and-thirsty\" class=\"headerlink\" title=\"Tired and thirsty\"></a>Tired and thirsty</h4><p>What’s the matter, children?<br>We are tired and thirsty, Mum.<br>Sit down here.<br>Are you all right now?<br>No, we aren’t.<br>Look!<br>There’s an ice cream man.<br>Two ice cream please.<br>Here you are, children.<br>Thanks, Mum.<br>These ice creams are nice.<br>Are you all right now?<br>Yes, we are, thank you.</p>\n<h4 id=\"Which-book\"><a href=\"#Which-book\" class=\"headerlink\" title=\"Which book\"></a>Which book</h4><p>Give me a book please, Jane.<br>Which book?<br>This one?<br>No, not that one. The red one.<br>This one?<br>Yes, please.<br>Here you are.<br>Thank you.</p>\n<h4 id=\"Which-glasses\"><a href=\"#Which-glasses\" class=\"headerlink\" title=\"Which glasses\"></a>Which glasses</h4><p>Give me some glasses please, Jane.<br>which glasses?<br>These glasses?<br>No, not these. The ones on the shelf.<br>These?<br>Yes, please.<br>Here you are.<br>Thanks.</p>\n<h4 id=\"Mrs-Smith’s-kitchen\"><a href=\"#Mrs-Smith’s-kitchen\" class=\"headerlink\" title=\"Mrs Smith’s kitchen\"></a>Mrs Smith’s kitchen</h4><p>Mrs. Smith’s kitchen is small.<br>There is a refrigerator in the kitchen.<br>The refrigerator is white.<br>It is on the right.<br>There is an electric cooker in the kitchen.<br>The cooker is blue.<br>It is on the left.<br>There is a table in the middle of the room.<br>There is a bottle on the table.<br>The bottle is empty.<br>There is a cup on the table, too.<br>The cup is clean.</p>\n",
            "tags": [
                "抄书",
                "练字"
            ]
        }
    ]
}